datakit/__init__.py
datakit/command_helpers.py
datakit/datakit_app.py
datakit/help.py
datakit/main.py
datakit/utils.py
datakit_core-0.3.2.dist-info/AUTHORS.rst
datakit_core-0.3.2.dist-info/LICENSE
datakit_core-0.3.2.dist-info/METADATA
datakit_core-0.3.2.dist-info/WHEEL
datakit_core-0.3.2.dist-info/entry_points.txt
datakit_core-0.3.2.dist-info/top_level.txt
datakit_core-0.3.2.dist-info/RECORD
