Metadata-Version: 2.1
Name: datakit-core
Version: 0.3.2
Summary: A pluggable command-line tool for custom data science workflows.
Home-page: https://github.com/associatedpress/datakit-core
Author: Serdar Tumgoren
Author-email: zstumgoren@gmail.com
License: ISCL
Keywords: datakit
Platform: UNKNOWN
Classifier: Development Status :: 3 - Alpha
Classifier: Intended Audience :: Developers
Classifier: License :: OSI Approved :: ISC License (ISCL)
Classifier: Natural Language :: English
Classifier: Programming Language :: Python :: 3.8
Classifier: Programming Language :: Python :: 3.9
Classifier: Programming Language :: Python :: 3.10
Classifier: Programming Language :: Python :: 3.11
Classifier: Environment :: Console
Requires-Dist: cliff
